grafana_dashboard/__init__.py
grafana_dashboard/extracted_generated_common_models.py
grafana_dashboard/grafana_dashboard.py
grafana_dashboard/manual_models.py
grafana_dashboard/utils.py
grafana_dashboard/converter/__init__.py
grafana_dashboard/converter/json_to_python.py
grafana_dashboard/converter/python_to_json.py
grafana_dashboard/model/__init__.py
grafana_dashboard/model/alertgroupspanelcfg_types_gen.py
grafana_dashboard/model/annotationslistpanelcfg_types_gen.py
grafana_dashboard/model/azuremonitordataquery_types_gen.py
grafana_dashboard/model/barchartpanelcfg_types_gen.py
grafana_dashboard/model/bargaugepanelcfg_types_gen.py
grafana_dashboard/model/cloudwatchdataquery_types_gen.py
grafana_dashboard/model/dashboard_types_gen.py
grafana_dashboard/model/dashboardlistpanelcfg_types_gen.py
grafana_dashboard/model/datagridpanelcfg_types_gen.py
grafana_dashboard/model/debugpanelcfg_types_gen.py
grafana_dashboard/model/elasticsearchdataquery_types_gen.py
grafana_dashboard/model/gaugepanelcfg_types_gen.py
grafana_dashboard/model/geomappanelcfg_types_gen.py
grafana_dashboard/model/grafanapyroscopedataquery_types_gen.py
grafana_dashboard/model/heatmappanelcfg_types_gen.py
grafana_dashboard/model/histogrampanelcfg_types_gen.py
grafana_dashboard/model/librarypanel_types_gen.py
grafana_dashboard/model/logspanelcfg_types_gen.py
grafana_dashboard/model/lokidataquery_types_gen.py
grafana_dashboard/model/newspanelcfg_types_gen.py
grafana_dashboard/model/nodegraphpanelcfg_types_gen.py
grafana_dashboard/model/parcadataquery_types_gen.py
grafana_dashboard/model/piechartpanelcfg_types_gen.py
grafana_dashboard/model/playlist_types_gen.py
grafana_dashboard/model/preferences_types_gen.py
grafana_dashboard/model/prometheusdataquery_types_gen.py
grafana_dashboard/model/publicdashboard_types_gen.py
grafana_dashboard/model/serviceaccount_types_gen.py
grafana_dashboard/model/statetimelinepanelcfg_types_gen.py
grafana_dashboard/model/statpanelcfg_types_gen.py
grafana_dashboard-0.1.1.dist-info/LICENSE
grafana_dashboard-0.1.1.dist-info/METADATA
grafana_dashboard-0.1.1.dist-info/WHEEL
grafana_dashboard-0.1.1.dist-info/entry_points.txt
grafana_dashboard-0.1.1.dist-info/top_level.txt
grafana_dashboard-0.1.1.dist-info/RECORD
