Metadata-Version: 2.1
Name: grafana-dashboard
Version: 0.1.1
Summary: Write Grafana dashboards in Python, without losing thousands of dashboards in the zoo
Home-page: https://github.com/fzyzcjy/grafana-dashboard-python
Author: fzyzcjy
License: MIT
Keywords: grafana dashboard json
Classifier: Development Status :: 4 - Beta
Classifier: Intended Audience :: Developers
Classifier: License :: OSI Approved :: MIT License
Classifier: Programming Language :: Python :: 3.6
Classifier: Programming Language :: Python :: 3.7
Classifier: Programming Language :: Python :: 3.8
Classifier: Programming Language :: Python :: 3.9
Classifier: Programming Language :: Python :: 3.10
Requires-Python: >=3.6
License-File: LICENSE
Requires-Dist: pydantic (>=1.10.2)
Requires-Dist: rich (>=13.4.2)
Requires-Dist: typer (>=0.6.1)
